anvl.py
anvl-1.0.dist-info/LICENSE
anvl-1.0.dist-info/METADATA
anvl-1.0.dist-info/WHEEL
anvl-1.0.dist-info/top_level.txt
anvl-1.0.dist-info/RECORD
