Metadata-Version: 2.1
Name: anvl
Version: 1.0
Summary: A module for reading and writing ANVL files and strings
Home-page: https://github.com/wtee/anvl
Author: wtee
License: Unlicense
Platform: UNKNOWN
License-File: LICENSE
